krotov/__init__.py
krotov/convergence.py
krotov/conversions.py
krotov/functionals.py
krotov/info_hooks.py
krotov/mu.py
krotov/objectives.py
krotov/optimize.py
krotov/parallelization.py
krotov/propagators.py
krotov/result.py
krotov/second_order.py
krotov/shapes.py
krotov-1.3.0.dist-info/METADATA
krotov-1.3.0.dist-info/WHEEL
krotov-1.3.0.dist-info/licenses/AUTHORS.rst
krotov-1.3.0.dist-info/licenses/LICENSE
krotov-1.3.0.dist-info/RECORD
