Metadata-Version: 2.3
Name: krotov
Version: 1.3.0
Summary: Python implementation of Krotov's method for quantum optimal control
Project-URL: Documentation, https://qucontrol.github.io/krotov/
Project-URL: Issues, https://github.com/qucontrol/krotov/issues
Project-URL: Source, https://github.com/qucontrol/krotov
Author-email: Michael Goerz <mail@michaelgoerz.net>
License: BSD License
License-File: AUTHORS.rst
License-File: LICENSE
Classifier: Development Status :: 5 - Production/Stable
Classifier: Framework :: Jupyter
Classifier: Intended Audience :: Education
Classifier: Intended Audience :: Science/Research
Classifier: License :: OSI Approved :: BSD License
Classifier: Natural Language :: English
Classifier: Operating System :: OS Independent
Classifier: Programming Language :: Python :: 3.8
Classifier: Programming Language :: Python :: 3.9
Classifier: Topic :: Scientific/Engineering
Classifier: Topic :: Scientific/Engineering :: Physics
Requires-Python: >=3.7
Requires-Dist: glom
Requires-Dist: grapheme
Requires-Dist: numpy
Requires-Dist: qutip<5.0,>=4.3.1
Requires-Dist: scipy
Requires-Dist: threadpoolctl
Provides-Extra: dev
Requires-Dist: codecov; extra == 'dev'
Requires-Dist: coverage<5.0; extra == 'dev'
Requires-Dist: ipython; extra == 'dev'
Requires-Dist: jupyter; extra == 'dev'
Requires-Dist: loky~=2.9; extra == 'dev'
Requires-Dist: nbval==0.11.0; extra == 'dev'
Requires-Dist: pytest-cov<=2.6.1; extra == 'dev'
Requires-Dist: pytest-xdist; extra == 'dev'
Requires-Dist: pytest==7.4.4; extra == 'dev'
Requires-Dist: weylchamber>=0.3.2; extra == 'dev'
Provides-Extra: docs
Requires-Dist: better-apidoc==0.3.2; extra == 'docs'
Requires-Dist: docs-versions-menu==0.5.2; extra == 'docs'
Requires-Dist: docutils<=0.17; extra == 'docs'
Requires-Dist: gitpython==3.1.43; extra == 'docs'
Requires-Dist: ipython; extra == 'docs'
Requires-Dist: jinja2==3.0.3; extra == 'docs'
Requires-Dist: matplotlib==3.7.5; extra == 'docs'
Requires-Dist: nbsphinx==0.9.3; extra == 'docs'
Requires-Dist: pybtex==0.24.0; extra == 'docs'
Requires-Dist: sphinx-autobuild; extra == 'docs'
Requires-Dist: sphinx-copybutton; extra == 'docs'
Requires-Dist: sphinx-rtd-theme; extra == 'docs'
Requires-Dist: sphinx<4.0; extra == 'docs'
Requires-Dist: sphinxcontrib-bibtex; extra == 'docs'
Requires-Dist: watermark~=2.4; extra == 'docs'
Requires-Dist: zip-files==0.4.1; extra == 'docs'
Provides-Extra: lint
Requires-Dist: black==22.1.0; extra == 'lint'
Requires-Dist: click==8.0.4; extra == 'lint'
Requires-Dist: flake8; extra == 'lint'
Requires-Dist: flake8-pyproject; extra == 'lint'
Requires-Dist: isort==4.3.*; extra == 'lint'
Requires-Dist: pylint~=2.6.0; extra == 'lint'
